yellowdb/__init__.py
yellowdb/py.typed
yellowdb/api/__init__.py
yellowdb/api/batch.py
yellowdb/api/database.py
yellowdb/api/iterator.py
yellowdb/cache/__init__.py
yellowdb/cache/write_through.py
yellowdb/compaction/__init__.py
yellowdb/compaction/compactor.py
yellowdb/core/__init__.py
yellowdb/core/bloom_filter.py
yellowdb/core/serializer.py
yellowdb/storage/__init__.py
yellowdb/storage/index.py
yellowdb/storage/memtable.py
yellowdb/storage/sstable.py
yellowdb/storage/wal.py
yellowdb/utils/__init__.py
yellowdb/utils/config.py
yellowdb/utils/exceptions.py
yellowdb/utils/logger.py
yellowdb-1.0.0.dist-info/licenses/LICENSE
yellowdb-1.0.0.dist-info/METADATA
yellowdb-1.0.0.dist-info/WHEEL
yellowdb-1.0.0.dist-info/top_level.txt
yellowdb-1.0.0.dist-info/RECORD
