Metadata-Version: 2.4
Name: yellowdb
Version: 1.0.0
Summary: A high-performance LSM-tree based key-value database written in Python
Author-email: Arshia Ahmadzadeh <squirrelspirits@gmail.com>
License: MIT License
Project-URL: Homepage, https://github.com/arshia-ahmadzadeh/yellowdb
Project-URL: Repository, https://github.com/arshia-ahmadzadeh/yellowdb.git
Project-URL: Bug Tracker, https://github.com/arshia-ahmadzadeh/yellowdb/issues
Project-URL: Documentation, https://github.com/arshia-ahmadzadeh/yellowdb#readme
Keywords: database,key-value,lsm-tree,storage,in-memory,performance,embedded
Classifier: Development Status :: 4 - Beta
Classifier: Intended Audience :: Developers
Classifier: License :: OSI Approved :: MIT License
Classifier: Operating System :: OS Independent
Classifier: Programming Language :: Python :: 3
Classifier: Programming Language :: Python :: 3.8
Classifier: Programming Language :: Python :: 3.9
Classifier: Programming Language :: Python :: 3.10
Classifier: Programming Language :: Python :: 3.11
Classifier: Programming Language :: Python :: 3.12
Classifier: Topic :: Database
Classifier: Topic :: Software Development :: Libraries :: Python Modules
Requires-Python: >=3.11
License-File: LICENSE
Requires-Dist: sortedcontainers>=2.4.0
Provides-Extra: dev
Requires-Dist: ruff>=0.6.0; extra == "dev"
Requires-Dist: pre-commit>=3.0.0; extra == "dev"
Dynamic: license-file
